fibo_gavin_baker/.coverage
fibo_gavin_baker/__init__.py
fibo_gavin_baker/fibo_gavin_baker.py
fibo_gavin_baker/.pytest_cache/.gitignore
fibo_gavin_baker/.pytest_cache/CACHEDIR.TAG
fibo_gavin_baker/.pytest_cache/README.md
fibo_gavin_baker/.pytest_cache/v/cache/nodeids
fibo_gavin_baker/.pytest_cache/v/cache/stepwise
fibo_gavin_baker/__pycache__/__init__.cpython-311.pyc
fibo_gavin_baker/__pycache__/fibo_gavin_baker.cpython-311.pyc
fibo_gavin_baker-0.0.2.dist-info/LICENSE
fibo_gavin_baker-0.0.2.dist-info/METADATA
fibo_gavin_baker-0.0.2.dist-info/WHEEL
fibo_gavin_baker-0.0.2.dist-info/entry_points.txt
fibo_gavin_baker-0.0.2.dist-info/top_level.txt
fibo_gavin_baker-0.0.2.dist-info/RECORD
