Metadata-Version: 2.1
Name: fibo-gavin-baker
Version: 0.0.2
Summary: This package does amazing things.
Home-page: https://github.com/gavinbaker999/Projects
Author: Gavin Baker
Author-email: "Gavin Baker" <endhousesoftware999@gmail.com>
License: MIT
License-File: LICENSE
Requires-Dist: termcolor <2,>=1.1.0
